bittensor_config/__init__.py
bittensor_config/config_impl.py
bittensor_config-0.0.1.dist-info/LICENSE
bittensor_config-0.0.1.dist-info/METADATA
bittensor_config-0.0.1.dist-info/WHEEL
bittensor_config-0.0.1.dist-info/top_level.txt
bittensor_config-0.0.1.dist-info/RECORD
